file_process/__init__.py
file_process/utils.py
pzyutils-0.1.0.dist-info/LICENSE.txt
pzyutils-0.1.0.dist-info/METADATA
pzyutils-0.1.0.dist-info/WHEEL
pzyutils-0.1.0.dist-info/top_level.txt
pzyutils-0.1.0.dist-info/RECORD
