Metadata-Version: 2.2
Name: pzyutils
Version: 0.1.0
Summary: useful tool set
Home-page: https://github.com/pnightowl/pzyutils
Author: pengying
Author-email: 15970840304@163.com
Classifier: Programming Language :: Python :: 3
Classifier: License :: OSI Approved :: MIT License
Classifier: Operating System :: OS Independent
Requires-Python: >=3.6
License-File: LICENSE.txt
Requires-Dist: openpyxl>=3.1.5
Dynamic: author
Dynamic: author-email
Dynamic: classifier
Dynamic: description-content-type
Dynamic: home-page
Dynamic: requires-dist
Dynamic: requires-python
Dynamic: summary
